{
	"configurations" : 
	[
		{
			"directories" : 
			[
				{
					"build" : ".",
					"jsonFile" : "directory-.-Debug-f5ebdc15457944623624.json",
					"minimumCMakeVersion" : 
					{
						"string" : "3.10"
					},
					"projectIndex" : 0,
					"source" : ".",
					"targetIndexes" : 
					[
						0,
						1,
						2,
						3,
						4
					]
				}
			],
			"name" : "Debug",
			"projects" : 
			[
				{
					"directoryIndexes" : 
					[
						0
					],
					"name" : "ogdf-user-example",
					"targetIndexes" : 
					[
						0,
						1,
						2,
						3,
						4
					]
				}
			],
			"targets" : 
			[
				{
					"directoryIndex" : 0,
					"id" : "circuit::@6890427a1f51a3e7e1df",
					"jsonFile" : "target-circuit-Debug-d760bdfdcb6cc1b06ec5.json",
					"name" : "circuit",
					"projectIndex" : 0
				},
				{
					"directoryIndex" : 0,
					"id" : "constants::@6890427a1f51a3e7e1df",
					"jsonFile" : "target-constants-Debug-cc207a38342ccad5e9b9.json",
					"name" : "constants",
					"projectIndex" : 0
				},
				{
					"directoryIndex" : 0,
					"id" : "gate::@6890427a1f51a3e7e1df",
					"jsonFile" : "target-gate-Debug-494a8409a8a6cce9287d.json",
					"name" : "gate",
					"projectIndex" : 0
				},
				{
					"directoryIndex" : 0,
					"id" : "graph::@6890427a1f51a3e7e1df",
					"jsonFile" : "target-graph-Debug-8cf0b5d32597b5378286.json",
					"name" : "graph",
					"projectIndex" : 0
				},
				{
					"directoryIndex" : 0,
					"id" : "qubit_reuse::@6890427a1f51a3e7e1df",
					"jsonFile" : "target-qubit_reuse-Debug-6a3b7e58455b1af26e2c.json",
					"name" : "qubit_reuse",
					"projectIndex" : 0
				}
			]
		}
	],
	"kind" : "codemodel",
	"paths" : 
	{
		"build" : "/Users/ben/github/l2-MBQC-Qubit-Reuse/build",
		"source" : "/Users/ben/github/l2-MBQC-Qubit-Reuse"
	},
	"version" : 
	{
		"major" : 2,
		"minor" : 5
	}
}
